granny_pliers/__init__.py
granny_pliers/auth/__init__.py
granny_pliers/auth/auth_config.py
granny_pliers/auth/auth_error.py
granny_pliers/auth/auth_request.py
granny_pliers/auth/auth_response.py
granny_pliers/auth/jwt.py
granny_pliers/auth/permissions.py
granny_pliers/auth/roles.py
granny_pliers/auth/rsa_codec.py
granny_pliers/config/__init__.py
granny_pliers/config/abstract_config.py
granny_pliers/config/autowired_config.py
granny_pliers/config/logger_config.py
granny_pliers/config/project_environment.py
granny_pliers/logger/__init__.py
granny_pliers/logger/abstract_logger.py
granny_pliers/logger/log_processors.py
granny_pliers/models/__init__.py
granny_pliers/models/auth/__init__.py
granny_pliers/models/auth/user.py
granny_pliers/models/metrics/__init__.py
granny_pliers/models/metrics/confusion_matrix.py
granny_pliers/models/web/__init__.py
granny_pliers/models/web/web_service_health_status.py
granny_pliers/orm/__init__.py
granny_pliers/orm/abstract_http_client.py
granny_pliers/orm/abstract_http_repository.py
granny_pliers/orm/abstract_model.py
granny_pliers/orm/abstract_mongo_repository.py
granny_pliers/orm/abstract_repository.py
granny_pliers/orm/restful_http_client.py
granny_pliers/scheduler/__init__.py
granny_pliers/scheduler/abstract_schedule_object.py
granny_pliers/scheduler/abstract_scheduler.py
granny_pliers/scheduler/time_table.py
granny_pliers/testing/__init__.py
granny_pliers/testing/abstract_test_case.py
granny_pliers/testing/async_abstract_test_case.py
granny_pliers/tools/__init__.py
granny_pliers/tools/datetime_helper.py
granny_pliers/web/__init__.py
granny_pliers/web/abstract_status_web_service.py
granny_pliers/web/abstract_web_application.py
granny_pliers/web/abstract_web_service.py
granny_pliers/web/web_application_config.py
granny_pliers/worker/__init__.py
granny_pliers/worker/abstract_worker.py
granny_pliers-0.0.23.dist-info/LICENSE
granny_pliers-0.0.23.dist-info/METADATA
granny_pliers-0.0.23.dist-info/WHEEL
granny_pliers-0.0.23.dist-info/top_level.txt
granny_pliers-0.0.23.dist-info/RECORD
