Metadata-Version: 2.1
Name: granny-pliers
Version: 0.0.23
Summary: Set of tools
Author-email: Dmytro Stepanenko <dmitrijstepanenko@gmail.com>
License: Apache License
Project-URL: Homepage, https://gitlab.com/stepanenko-family/shared/granny-pliers.git
Project-URL: Documentation, https://gitlab.com/stepanenko-family/shared/granny-pliers.git
Keywords: logging,configuration,tools,tool-belt
Classifier: Intended Audience :: Developers
Classifier: License :: OSI Approved :: Apache Software License
Classifier: Operating System :: OS Independent
Classifier: Programming Language :: Python :: 3
Classifier: Programming Language :: Python :: 3.10
Classifier: Programming Language :: Python :: 3.11
Classifier: Topic :: Software Development :: Libraries :: Python Modules
Requires-Python: >=3.11
License-File: LICENSE
Requires-Dist: aiohttp >=3.9.3
Requires-Dist: cryptography >=42.0.2
Requires-Dist: dateparser >=1.2.0
Requires-Dist: motor ==3.3.2
Requires-Dist: structlog >=24.1.0
Requires-Dist: colorama >=0.4.6
Requires-Dist: jsonplus >=0.8.0
Requires-Dist: aiofiles >=23.2.0
Requires-Dist: PyYAML >=6.0
Provides-Extra: dev
Requires-Dist: black >=24.1.1 ; extra == 'dev'
Requires-Dist: coverage >=7.4.1 ; extra == 'dev'
Requires-Dist: pylint >=3.0.3 ; extra == 'dev'
Requires-Dist: pytest >=8.0.0 ; extra == 'dev'
Requires-Dist: pytest-cov ==4.1.0 ; extra == 'dev'
Requires-Dist: sphinx-rtd-theme ==2.0.0 ; extra == 'dev'
Requires-Dist: lumache ; extra == 'dev'
